sven/__init__.py
sven/__main__.py
sven/cli/agent.py
sven/cli/auth.py
sven/cli/client.py
sven/cli/main.py
sven/cli/tools.py
sven/client/client.py
sven/client/components.py
sven/client/api/client.py
sven/client/api/types.py
sven/tools/__init__.py
sven/tools/ask_user_tool.py
sven/tools/file_edit_tool.py
sven/tools/file_read_tool.py
sven/tools/file_write_tool.py
sven/tools/glob_tool.py
sven/tools/grep_tool.py
sven/tools/ls_tool.py
sven/tools/shell_tool.py
sven/tools/util/__init__.py
sven/tools/util/confirmation.py
sven_client-0.1.0.dist-info/METADATA
sven_client-0.1.0.dist-info/WHEEL
sven_client-0.1.0.dist-info/entry_points.txt
sven_client-0.1.0.dist-info/top_level.txt
sven_client-0.1.0.dist-info/RECORD
