Metadata-Version: 2.2
Name: sven-client
Version: 0.1.0
Summary: Sven CLI client for agent automation
Author-email: Sven Team <info@swedishembedded.com>
License: MIT
Project-URL: Homepage, https://git.swedishembedded.com/core/platform/sven
Project-URL: Bug Tracker, https://git.swedishembedded.com/core/platform/sven/-/issues
Classifier: Programming Language :: Python :: 3
Classifier: License :: OSI Approved :: MIT License
Classifier: Operating System :: OS Independent
Requires-Python: >=3.8
Requires-Dist: requests>=2.28.0
Requires-Dist: rich
Requires-Dist: httpx<0.28.0,>=0.24.0
Requires-Dist: pydantic>=2.0.0
Requires-Dist: python-dotenv>=1.0.0
Requires-Dist: tabulate
Requires-Dist: langchain>=0.2.0
Requires-Dist: langchain-openai>=0.2.0
Requires-Dist: langchain-anthropic>=0.2.0
Requires-Dist: langchain-community>=0.2.0
Requires-Dist: anthropic
Requires-Dist: mcp
Provides-Extra: dev
Requires-Dist: pytest>=7.0.0; extra == "dev"
Requires-Dist: pytest-cov>=4.0.0; extra == "dev"
Requires-Dist: black>=23.0.0; extra == "dev"
Requires-Dist: isort>=5.12.0; extra == "dev"
Requires-Dist: mypy>=1.0.0; extra == "dev"
Requires-Dist: ruff>=0.0.270; extra == "dev"
Requires-Dist: pre-commit>=3.0.0; extra == "dev"
Requires-Dist: bump2version>=1.0.0; extra == "dev"
Requires-Dist: tox>=4.0.0; extra == "dev"
Requires-Dist: build>=1.0.0; extra == "dev"
